Workbook

Sheet Sales_Data
A1: Order_ID | B1: Order_Date | C1: Region | D1: Sales_Channel | E1: Product | F1: Category | G1: Quantity | H1: Unit_Price | I1: Discount_Rate | J1: Unit_Cost | K1: Revenue | L1: Total_Cost | M1: Profit | N1: Profit_Margin
A2: ORD-0001 | B2: 45670 | C2: South | D2: Online | E2: Wireless Mouse | F2: Accessories | G2: 5 | H2: 25 | I2: 0 | J2: 14 | K2: =G2*H2 | L2: =G2*J2 | M2: =K2-L2 | N2: =IFERROR(M2/K2,0)
A3: ORD-0002 | B3: 46004 | C3: West | D3: Online | E3: Wireless Mouse | F3: Accessories | G3: 2 | H3: 21.25 | I3: 0.15 | J3: 14 | K3: =G3*H3 | L3: =G3*J3 | M3: =K3-L3 | N3: =IFERROR(M3/K3,0)
A4: ORD-0003 | B4: 45705 | C4: North | D4: Corporate | E4: Laptop Stand | F4: Accessories | G4: 4 | H4: 55 | I4: 0 | J4: 32 | K4: =G4*H4 | L4: =G4*J4 | M4: =K4-L4 | N4: =IFERROR(M4/K4,0)
A5: ORD-0004 | B5: 45990 | C5: West | D5: Corporate | E5: Monitor | F5: Electronics | G5: 7 | H5: 220 | I5: 0 | J5: 145 | K5: =G5*H5 | L5: =G5*J5 | M5: =K5-L5 | N5: =IFERROR(M5/K5,0)
A6: ORD-0005 | B6: 45661 | C6: East | D6: Retail | E6: USB-C Hub | F6: Electronics | G6: 3 | H6: 44.1 | I6: 0.1 | J6: 28 | K6: =G6*H6 | L6: =G6*J6 | M6: =K6-L6 | N6: =IFERROR(M6/K6,0)
A7: ORD-0006 | B7: 45768 | C7: North | D7: Retail | E7: Keyboard | F7: Accessories | G7: 6 | H7: 39 | I7: 0 | J7: 22 | K7: =G7*H7 | L7: =G7*J7 | M7: =K7-L7 | N7: =IFERROR(M7/K7,0)
A8: ORD-0007 | B8: 45841 | C8: East | D8: Online | E8: Wireless Mouse | F8: Accessories | G8: 6 | H8: 21.25 | I8: 0.15 | J8: 14 | K8: =G8*H8 | L8: =G8*J8 | M8: =K8-L8 | N8: =IFERROR(M8/K8,0)
A9: ORD-0008 | B9: 45932 | C9: North | D9: Corporate | E9: Desk Lamp | F9: Office | G9: 2 | H9: 37.8 | I9: 0.1 | J9: 24 | K9: =G9*H9 | L9: =G9*J9 | M9: =K9-L9 | N9: =IFERROR(M9/K9,0)
A10: ORD-0009 | B10: 45979 | C10: South | D10: Corporate | E10: USB-C Hub | F10: Electronics | G10: 6 | H10: 41.65 | I10: 0.15 | J10: 28 | K10: =G10*H10 | L10: =G10*J10 | M10: =K10-L10 | N10: =IFERROR(M10/K10,0)
A11: ORD-0010 | B11: 45681 | C11: North | D11: Online | E11: Wireless Mouse | F11: Accessories | G11: 4 | H11: 23.75 | I11: 0.05 | J11: 14 | K11: =G11*H11 | L11: =G11*J11 | M11: =K11-L11 | N11: =IFERROR(M11/K11,0)
A12: ORD-0011 | B12: 45852 | C12: East | D12: Online | E12: Wireless Mouse | F12: Accessories | G12: 5 | H12: 22.5 | I12: 0.1 | J12: 14 | K12: =G12*H12 | L12: =G12*J12 | M12: =K12-L12 | N12: =IFERROR(M12/K12,0)
A13: ORD-0012 | B13: 45839 | C13: North | D13: Corporate | E13: Headphones | F13: Electronics | G13: 4 | H13: 75.05 | I13: 0.05 | J13: 48 | K13: =G13*H13 | L13: =G13*J13 | M13: =K13-L13 | N13: =IFERROR(M13/K13,0)
... A301: ORD-0300 | B301: 45939 | C301: South | D301: Corporate | E301: Wireless Mouse | F301: Accessories | G301: 5 | H301: 23.75 | I301: 0.05 | J301: 14 | K301: =G301*H301 | L301: =G301*J301 | M301: =K301-L301 | N301: =IFERROR(M301/K301,0)

Sheet Dashboard
A1: 2025 SALES PERFORMANCE | PORTFOLIO PROJECT
A3: Key Performance Indicators
A4: Total Revenue | B4: =SUM(Sales_Data!K2:K301)
A5: Total Profit | B5: =SUM(Sales_Data!M2:M301)
A6: Orders | B6: =COUNTA(Sales_Data!A2:A301)
A7: Average Order Revenue | B7: =AVERAGE(Sales_Data!K2:K301)
A8: Overall Profit Margin | B8: =IFERROR(SUM(Sales_Data!M2:M301)/SUM(Sales_Data!K2:K301),0)
A11: Revenue by Region | D11: Revenue by Category
A12: Region | B12: Revenue | D12: Category | E12: Revenue
A13: North | B13: =SUMIF(Sales_Data!C$2:C$301,A13,Sales_Data!K$2:K$301) | D13: Accessories | E13: =SUMIF(Sales_Data!F$2:F$301,D13,Sales_Data!K$2:K$301)
A14: South | B14: =SUMIF(Sales_Data!C$2:C$301,A14,Sales_Data!K$2:K$301) | D14: Electronics | E14: =SUMIF(Sales_Data!F$2:F$301,D14,Sales_Data!K$2:K$301)
A15: East | B15: =SUMIF(Sales_Data!C$2:C$301,A15,Sales_Data!K$2:K$301) | D15: Office | E15: =SUMIF(Sales_Data!F$2:F$301,D15,Sales_Data!K$2:K$301)
A16: West | B16: =SUMIF(Sales_Data!C$2:C$301,A16,Sales_Data!K$2:K$301) | D16: Stationery | E16: =SUMIF(Sales_Data!F$2:F$301,D16,Sales_Data!K$2:K$301)
